AUTHORS.rst
CONTRIBUTING.rst
HISTORY.rst
LICENSE
MANIFEST.in
README.md
setup.cfg
setup.py
easyrbac/__init__.py
easyrbac/acl.py
easyrbac/model.py
easyrbac.egg-info/PKG-INFO
easyrbac.egg-info/SOURCES.txt
easyrbac.egg-info/dependency_links.txt
easyrbac.egg-info/top_level.txt
tests/__init__.py
tests/test_permissions.py
tests/test_role_assignment_deletion.py