Metadata-Version: 1.1
Name: easyrbac
Version: 0.1.0
Summary: easyrbac: Role Based Access Control for humans
Home-page: https://github.com/prodicus/easyrbac
Author: Tasdik Rahman
Author-email: prodicus@outlook.com
License: GPLv3
Download-URL: https://github.com/prodicus/easyrbac/tarball/0.1.0
Keywords: rbac
Platform: UNKNOWN
Classifier: Development Status :: 3 - Alpha
Classifier: Intended Audience :: Developers
Classifier: Natural Language :: English
Classifier: Programming Language :: Python
Classifier: Programming Language :: Python :: 2.6
Classifier: Programming Language :: Python :: 2.7
Classifier: Programming Language :: Python :: 3.4
Classifier: Programming Language :: Python :: 3.5
Classifier: Programming Language :: Python :: Implementation :: CPython
Classifier: Programming Language :: Python :: Implementation :: PyPy
Classifier: Topic :: Text Processing :: Linguistic
